{
  "title": "Clarify",
  "description": "开源文档发布工具，为 MDX 和 OpenAPI 而生。",
  "theme": {
    "primary": "#0ea5e9"
  },
  "navbar": {
    "links": [
      {
        "label": "文档",
        "href": "/getting-started"
      },
      {
        "label": "功能",
        "href": "/features"
      },
      {
        "label": "演示",
        "href": "/showcase"
      },
      {
        "label": "开发",
        "href": "/development"
      },
      {
        "label": "GitHub",
        "href": "https://github.com/taicode-labs/clarify",
        "external": true
      }
    ]
  }
}
